README.md
setup.py
yuhanutils/__init__.py
yuhanutils/yuhanutils.py
yuhanutils.egg-info/PKG-INFO
yuhanutils.egg-info/SOURCES.txt
yuhanutils.egg-info/dependency_links.txt
yuhanutils.egg-info/top_level.txt