Metadata-Version: 1.0
Name: yuhanutils
Version: 0.0.1
Summary: Some useful utilities put together by Yuhan Chen
Home-page: UNKNOWN
Author: Yuhan Chen
Author-email: chenyh@umich.edu
License: UNKNOWN
Platform: UNKNOWN
